syncurity_utils/__init__.py
syncurity_utils/__version__.py
syncurity_utils/api.py
syncurity_utils/exceptions.py
syncurity_utils/models.py
syncurity_utils/typecheck.py
syncurity_utils/typecheck_py2.py
syncurity_utils/utils.py
syncurity_utils/db/__init__.py
syncurity_utils/db/alert.py
syncurity_utils/db/alert_type.py
syncurity_utils/db/base.py
syncurity_utils/db/db.py
syncurity_utils-0.4.1.dist-info/METADATA
syncurity_utils-0.4.1.dist-info/WHEEL
syncurity_utils-0.4.1.dist-info/top_level.txt
syncurity_utils-0.4.1.dist-info/RECORD
