Metadata-Version: 2.1
Name: syncurity-utils
Version: 0.4.1
Summary: Syncurity Common Util Classes and Functions
Home-page: https://github.com/syncurity/syncurity-utils
Author: Syncurity
Author-email: support@syncurity.net
Maintainer: Syncurity
Maintainer-email: support@syncurity.net
License: Apache 2.0
Keywords: Security SOAR Utilities IR-Flow Automation Orchestration
Platform: any
Classifier: Development Status :: 4 - Beta
Classifier: Intended Audience :: Developers
Classifier: Topic :: Security
Classifier: Natural Language :: English
Classifier: License :: OSI Approved :: Apache Software License
Classifier: Programming Language :: Python
Classifier: Programming Language :: Python :: 2
Classifier: Programming Language :: Python :: 2.7
Classifier: Programming Language :: Python :: 3
Classifier: Programming Language :: Python :: 3.6
Classifier: Programming Language :: Python :: 3.7
Classifier: Programming Language :: Python :: Implementation :: CPython
Classifier: Programming Language :: Python :: Implementation :: PyPy
Requires-Python: >=2.7.*, !=3.0.*, !=3.1.*, !=3.2.*, !=3.3.*, !=3.4.*, !=3.5.*
Requires-Dist: validators (>=0.12.5)
Requires-Dist: irflow-client (<1.6,>=1.5.10)
Requires-Dist: sqlalchemy (==1.3.8)
Requires-Dist: SQLAlchemy-Utils (==0.34.2)
Requires-Dist: psycopg2 (==2.8.3)
